{
  "schema": 1,
  "generated": "2026-07-15T08:23:23Z",
  "poly": {
    "block": 90265872,
    "rebase": {
      "pctPerEpoch": 0.1495,
      "sched": 0.1375,
      "epochH": 6
    },
    "extra": {
      "long360": {
        "pctPerEpoch": 0.12,
        "epochH": 12,
        "globalIndex": "196000000",
        "epoch": 2381,
        "denom": "1000000000"
      },
      "long600": {
        "pctPerEpoch": 0.0703,
        "epochH": 12,
        "globalIndex": "547787000",
        "epoch": 2381,
        "denom": "1000000000"
      }
    }
  },
  "anubis": {
    "block": 8576312,
    "rebase": {
      "pctPerEpoch": 0.1626,
      "epochH": 6,
      "index": 846.38695
    },
    "extra": {
      "long360": {
        "pctPerEpoch": 0.15,
        "epochH": 12,
        "globalIndex": "220000000",
        "epoch": 2381,
        "denom": "1000000000"
      },
      "long600": {
        "pctPerEpoch": 0.195,
        "epochH": 12,
        "globalIndex": "282100000",
        "epoch": 2381,
        "denom": "1000000000"
      }
    }
  }
}