{
  "schema": 1,
  "generated": "2026-07-23T08:38:14Z",
  "poly": {
    "block": 90727266,
    "rebase": {
      "pctPerEpoch": 0.1499,
      "sched": 0.1369,
      "epochH": 6
    },
    "extra": {
      "long360": {
        "pctPerEpoch": 0.12,
        "epochH": 12,
        "globalIndex": "215200000",
        "epoch": 2397,
        "denom": "1000000000"
      },
      "long600": {
        "pctPerEpoch": 0.0679,
        "epochH": 12,
        "globalIndex": "558831000",
        "epoch": 2397,
        "denom": "1000000000"
      }
    }
  },
  "anubis": {
    "block": 9268250,
    "rebase": {
      "pctPerEpoch": 0.1498,
      "epochH": 6.0,
      "index": 887.931328,
      "epoch": 2527,
      "lut": 1784776479
    },
    "extra": {
      "long360": {
        "pctPerEpoch": 0.15,
        "epochH": 12,
        "globalIndex": "244000000",
        "epoch": 2397,
        "denom": "1000000000"
      },
      "long600": {
        "pctPerEpoch": 0.195,
        "epochH": 12,
        "globalIndex": "313300000",
        "epoch": 2397,
        "denom": "1000000000"
      }
    }
  }
}